aliyunsdkgovernance/__init__.py
aliyunsdkgovernance/endpoint.py
aliyunsdkgovernance/request/__init__.py
aliyunsdkgovernance/request/v20210120/BatchEnrollAccountsRequest.py
aliyunsdkgovernance/request/v20210120/CreateAccountFactoryBaselineRequest.py
aliyunsdkgovernance/request/v20210120/DeleteAccountFactoryBaselineRequest.py
aliyunsdkgovernance/request/v20210120/EnrollAccountRequest.py
aliyunsdkgovernance/request/v20210120/GetAccountFactoryBaselineRequest.py
aliyunsdkgovernance/request/v20210120/GetEnrolledAccountRequest.py
aliyunsdkgovernance/request/v20210120/ListAccountFactoryBaselineItemsRequest.py
aliyunsdkgovernance/request/v20210120/ListAccountFactoryBaselinesRequest.py
aliyunsdkgovernance/request/v20210120/ListEnrolledAccountsRequest.py
aliyunsdkgovernance/request/v20210120/ListEvaluationMetadataRequest.py
aliyunsdkgovernance/request/v20210120/ListEvaluationMetricDetailsRequest.py
aliyunsdkgovernance/request/v20210120/ListEvaluationResultsRequest.py
aliyunsdkgovernance/request/v20210120/ListEvaluationScoreHistoryRequest.py
aliyunsdkgovernance/request/v20210120/RunEvaluationRequest.py
aliyunsdkgovernance/request/v20210120/UpdateAccountFactoryBaselineRequest.py
aliyunsdkgovernance/request/v20210120/__init__.py
aliyun_python_sdk_governance-1.0.0.dist-info/LICENSE
aliyun_python_sdk_governance-1.0.0.dist-info/METADATA
aliyun_python_sdk_governance-1.0.0.dist-info/WHEEL
aliyun_python_sdk_governance-1.0.0.dist-info/top_level.txt
aliyun_python_sdk_governance-1.0.0.dist-info/RECORD
